{
  "$schema" : "http://json-schema.org/draft-07/schema#",
  "type" : "object",
  "properties" : {
    "data_type" : {
      "type" : "string"
    },
    "time_series_length" : {
      "type" : "integer"
    },
    "data" : {
      "type" : "array",
      "items" : [
        {
          "type" : "object",
          "properties" : {
            "id" : {
              "type" : "string"
            },
            "id_data" : {
              "type" : "array",
              "items" : [
                {
                  "type" : "object",
                  "properties" : {
                    "segment" : {
                      "type" : "null"
                    },
                    "metrics" : {
                      "type" : "object",
                      "properties" : {
                        "impressions" : {
                          "type" : "null"
                        },
                        "tweets_send" : {
                          "type" : "null"
                        },
                        "billed_charge_local_micro" : {
                          "type" : "null"
                        },
                        "qualified_impressions" : {
                          "type" : "null"
                        },
                        "follows" : {
                          "type" : "null"
                        },
                        "app_clicks" : {
                          "type" : "null"
                        },
                        "retweets" : {
                          "type" : "null"
                        },
                        "unfollows" : {
                          "type" : "null"
                        },
                        "likes" : {
                          "type" : "null"
                        },
                        "engagements" : {
                          "type" : "null"
                        },
                        "clicks" : {
                          "type" : "null"
                        },
                        "card_engagements" : {
                          "type" : "null"
                        },
                        "poll_card_vote" : {
                          "type" : "null"
                        },
                        "replies" : {
                          "type" : "null"
                        },
                        "url_clicks" : {
                          "type" : "null"
                        },
                        "billed_engagements" : {
                          "type" : "null"
                        },
                        "carousel_swipes" : {
                          "type" : "null"
                        }
                      },
                      "required" : [
                        "impressions",
                        "tweets_send",
                        "billed_charge_local_micro",
                        "qualified_impressions",
                        "follows",
                        "app_clicks",
                        "retweets",
                        "unfollows",
                        "likes",
                        "engagements",
                        "clicks",
                        "card_engagements",
                        "poll_card_vote",
                        "replies",
                        "url_clicks",
                        "billed_engagements",
                        "carousel_swipes"
                      ]
                    }
                  },
                  "required" : [
                    "segment",
                    "metrics"
                  ]
                }
              ]
            }
          },
          "required" : [
            "id",
            "id_data"
          ]
        },
        {
          "type" : "object",
          "properties" : {
            "id" : {
              "type" : "string"
            },
            "id_data" : {
              "type" : "array",
              "items" : [
                {
                  "type" : "object",
                  "properties" : {
                    "segment" : {
                      "type" : "null"
                    },
                    "metrics" : {
                      "type" : "object",
                      "properties" : {
                        "impressions" : {
                          "type" : "null"
                        },
                        "tweets_send" : {
                          "type" : "null"
                        },
                        "billed_charge_local_micro" : {
                          "type" : "null"
                        },
                        "qualified_impressions" : {
                          "type" : "null"
                        },
                        "follows" : {
                          "type" : "null"
                        },
                        "app_clicks" : {
                          "type" : "null"
                        },
                        "retweets" : {
                          "type" : "null"
                        },
                        "unfollows" : {
                          "type" : "null"
                        },
                        "likes" : {
                          "type" : "null"
                        },
                        "engagements" : {
                          "type" : "null"
                        },
                        "clicks" : {
                          "type" : "null"
                        },
                        "card_engagements" : {
                          "type" : "null"
                        },
                        "poll_card_vote" : {
                          "type" : "null"
                        },
                        "replies" : {
                          "type" : "null"
                        },
                        "url_clicks" : {
                          "type" : "null"
                        },
                        "billed_engagements" : {
                          "type" : "null"
                        },
                        "carousel_swipes" : {
                          "type" : "null"
                        }
                      },
                      "required" : [
                        "impressions",
                        "tweets_send",
                        "billed_charge_local_micro",
                        "qualified_impressions",
                        "follows",
                        "app_clicks",
                        "retweets",
                        "unfollows",
                        "likes",
                        "engagements",
                        "clicks",
                        "card_engagements",
                        "poll_card_vote",
                        "replies",
                        "url_clicks",
                        "billed_engagements",
                        "carousel_swipes"
                      ]
                    }
                  },
                  "required" : [
                    "segment",
                    "metrics"
                  ]
                }
              ]
            }
          },
          "required" : [
            "id",
            "id_data"
          ]
        }
      ]
    },
    "request" : {
      "type" : "object",
      "properties" : {
        "params" : {
          "type" : "object",
          "properties" : {
            "start_time" : {
              "type" : "string"
            },
            "segmentation_type" : {
              "type" : "null"
            },
            "entity_ids" : {
              "type" : "array",
              "items" : [
                {
                  "type" : "string"
                },
                {
                  "type" : "string"
                }
              ]
            },
            "end_time" : {
              "type" : "string"
            },
            "country" : {
              "type" : "null"
            },
            "placement" : {
              "type" : "string"
            },
            "granularity" : {
              "type" : "string"
            },
            "entity" : {
              "type" : "string"
            },
            "platform" : {
              "type" : "null"
            },
            "metric_groups" : {
              "type" : "array",
              "items" : [
                {
                  "type" : "string"
                },
                {
                  "type" : "string"
                }
              ]
            }
          },
          "required" : [
            "start_time",
            "segmentation_type",
            "entity_ids",
            "end_time",
            "country",
            "placement",
            "granularity",
            "entity",
            "platform",
            "metric_groups"
          ]
        }
      },
      "required" : [
        "params"
      ]
    }
  },
  "required" : [
    "data_type",
    "time_series_length",
    "data",
    "request"
  ]
}